agentine/__init__.py
agentine/agent.py
agentine/chatbot.py
agentine/config.py
agentine/llm.py
agentine/message.py
agentine/metadata.py
agentine/utils.py
agentine-0.1.15.dist-info/licenses/LICENSE
agentine-0.1.15.dist-info/METADATA
agentine-0.1.15.dist-info/WHEEL
agentine-0.1.15.dist-info/top_level.txt
agentine-0.1.15.dist-info/RECORD
