Metadata-Version: 2.4
Name: agentine
Version: 0.1.15
Summary: agentine is a lightweight Python library that enables quick and easy creation of model-agnostic AI agents.
Home-page: https://github.com/vincentdeneuf/agentine
Author: Vincent de Neuf
Author-email: 0189vn@gmail.com
License: MIT
Classifier: Programming Language :: Python :: 3
Classifier: License :: OSI Approved :: MIT License
Classifier: Operating System :: OS Independent
Requires-Python: >=3.6
License-File: LICENSE
Requires-Dist: pydantic
Requires-Dist: openai
Requires-Dist: print9
Requires-Dist: python-dotenv
Dynamic: license-file
